{
  "id": "emma-playbooks",
  "name": "Emma's Playbooks",
  "description": "Plugin library of skills/playbooks for Emma to use and refer to to do her work as an SDR.",
  "version": "0.1.0",
  "configSchema": {
    "type": "object",
    "additionalProperties": false,
    "properties": {}
  },
  "skills": [
    "skills/sdr-cold-call",
    "skills/sdr-cold-email",
    "skills/sdr-hubspot-hygiene",
    "skills/sdr-like-audience-list",
    "skills/sdr-reactivation-list",
    "skills/team-meet-and-greet"
  ]
}
